CHANGELOG.md
LICENSE
isort/__init__.py
isort/__main__.py
isort/_future/__init__.py
isort/_future/_dataclasses.py
isort/_vendored/tomli/LICENSE
isort/_vendored/tomli/__init__.py
isort/_vendored/tomli/_parser.py
isort/_vendored/tomli/_re.py
isort/_vendored/tomli/py.typed
isort/_version.py
isort/api.py
isort/comments.py
isort/core.py
isort/deprecated/__init__.py
isort/deprecated/finders.py
isort/exceptions.py
isort/files.py
isort/format.py
isort/hooks.py
isort/identify.py
isort/io.py
isort/literal.py
isort/logo.py
isort/main.py
isort/output.py
isort/parse.py
isort/place.py
isort/profiles.py
isort/py.typed
isort/pylama_isort.py
isort/sections.py
isort/settings.py
isort/setuptools_commands.py
isort/sorting.py
isort/stdlibs/__init__.py
isort/stdlibs/all.py
isort/stdlibs/py2.py
isort/stdlibs/py27.py
isort/stdlibs/py3.py
isort/stdlibs/py310.py
isort/stdlibs/py311.py
isort/stdlibs/py35.py
isort/stdlibs/py36.py
isort/stdlibs/py37.py
isort/stdlibs/py38.py
isort/stdlibs/py39.py
isort/utils.py
isort/wrap.py
isort/wrap_modes.py
isort-5.11.0.dist-info/LICENSE
isort-5.11.0.dist-info/WHEEL
isort-5.11.0.dist-info/METADATA
isort-5.11.0.dist-info/entry_points.txt
isort-5.11.0.dist-info/RECORD
