Metadata-Version: 2.1
Name: isort
Version: 5.11.0
Summary: A Python utility / library to sort Python imports.
Home-page: https://pycqa.github.io/isort/
License: MIT
Keywords: Refactor,Lint,Imports,Sort,Clean
Author: Timothy Crosley
Author-email: timothy.crosley@gmail.com
Requires-Python: >=3.7.0
Classifier: Development Status :: 6 - Mature
Classifier: Environment :: Console
Classifier: Intended Audience :: Developers
Classifier: License :: OSI Approved :: MIT License
Classifier: Natural Language :: English
Classifier: Programming Language :: Python
Classifier: Programming Language :: Python :: 3
Classifier: Programming Language :: Python :: 3.7
Classifier: Programming Language :: Python :: 3.8
Classifier: Programming Language :: Python :: 3.9
Classifier: Programming Language :: Python :: 3.10
Classifier: Programming Language :: Python :: 3.11
Classifier: Programming Language :: Python :: 3
Classifier: Programming Language :: Python :: 3 :: Only
Classifier: Programming Language :: Python :: 3.10
Classifier: Programming Language :: Python :: 3.11
Classifier: Programming Language :: Python :: 3.7
Classifier: Programming Language :: Python :: 3.8
Classifier: Programming Language :: Python :: 3.9
Classifier: Programming Language :: Python :: Implementation :: CPython
Classifier: Programming Language :: Python :: Implementation :: PyPy
Classifier: Topic :: Software Development :: Libraries
Classifier: Topic :: Utilities
Provides-Extra: colors
Provides-Extra: pipfile-deprecated-finder
Provides-Extra: plugins
Provides-Extra: requirements-deprecated-finder
Requires-Dist: colorama (>=0.4.3,<0.5.0) ; extra == "colors"
Requires-Dist: pip-api ; extra == "requirements-deprecated-finder"
Requires-Dist: pipreqs ; extra == "pipfile-deprecated-finder" or extra == "requirements-deprecated-finder"
Requires-Dist: requirementslib ; extra == "pipfile-deprecated-finder"
Requires-Dist: setuptools ; extra == "plugins"
Project-URL: Changelog, https://github.com/pycqa/isort/blob/main/CHANGELOG.md
Project-URL: Documentation, https://pycqa.github.io/isort/
Project-URL: Repository, https://github.com/pycqa/isort
